{"X/Sīlakkhandhavaggaabhinavaṭīkā/Brahmajālasutta/1": "X/X/Brahmajālasutta/1", "X/Sīlakkhandhavaggaabhinavaṭīkā/Brahmajālasutta/2": "X/X/Brahmajālasutta/2", "X/Sīlakkhandhavaggaabhinavaṭīkā/Brahmajālasutta/3": "X/Sīlakkhandhavaggapāḷi/Brahmajālasutta/3", "X/Sīlakkhandhavaggaabhinavaṭīkā/Brahmajālasutta/4": "X/Sīlakkhandhavaggapāḷi/Brahmajālasutta/4", "X/Sīlakkhandhavaggaabhinavaṭīkā/Brahmajālasutta/5": "X/Sīlakkhandhavaggapāḷi/Brahmajālasutta/5", "X/Sīlakkhandhavaggaabhinavaṭīkā/Brahmajālasutta/6": "X/Sīlakkhandhavaggapāḷi/Brahmajālasutta/6", "X/Sīlakkhandhavaggaabhinavaṭīkā/Brahmajālasutta/7": "X/Sīlakkhandhavaggapāḷi/Brahmajālasutta/7", "X/Sīlakkhandhavaggaabhinavaṭīkā/Brahmajālasutta/8": "X/Sīlakkhandhavaggapāḷi/Brahmajālasutta/8", "X/Sīlakkhandhavaggaabhinavaṭīkā/Brahmajālasutta/9": "X/Sīlakkhandhavaggapāḷi/Brahmajālasutta/9", "X/Sīlakkhandhavaggaabhinavaṭīkā/Brahmajālasutta/10": "X/Sīlakkhandhavaggapāḷi/Brahmajālasutta/10", "X/Sīlakkhandhavaggaabhinavaṭīkā/Brahmajālasutta/11": "X/Sīlakkhandhavaggapāḷi/Brahmajālasutta/11", "X/Sīlakkhandhavaggaabhinavaṭīkā/Brahmajālasutta/12": "X/Sīlakkhandhavaggapāḷi/Brahmajālasutta/12", "X/Sīlakkhandhavaggaabhinavaṭīkā/Brahmajālasutta/13": "X/Sīlakkhandhavaggapāḷi/Brahmajālasutta/13", "X/Sīlakkhandhavaggaabhinavaṭīkā/Brahmajālasutta/14": "X/Sīlakkhandhavaggapāḷi/Brahmajālasutta/14", "X/Sīlakkhandhavaggaabhinavaṭīkā/Brahmajālasutta/15": "X/Sīlakkhandhavaggapāḷi/Brahmajālasutta/15", "X/Sīlakkhandhavaggaabhinavaṭīkā/Brahmajālasutta/16": "X/Sīlakkhandhavaggapāḷi/Brahmajālasutta/16", "X/Sīlakkhandhavaggaabhinavaṭīkā/Brahmajālasutta/17": "X/Sīlakkhandhavaggapāḷi/Brahmajālasutta/17", "X/Sīlakkhandhavaggaabhinavaṭīkā/Brahmajālasutta/18": "X/Sīlakkhandhavaggapāḷi/Brahmajālasutta/18", "X/Sīlakkhandhavaggaabhinavaṭīkā/Brahmajālasutta/19": "X/Sīlakkhandhavaggapāḷi/Brahmajālasutta/19", "X/Sīlakkhandhavaggaabhinavaṭīkā/Brahmajālasutta/20": "X/Sīlakkhandhavaggapāḷi/Brahmajālasutta/20", "X/Sīlakkhandhavaggaabhinavaṭīkā/Brahmajālasutta/21": "X/Sīlakkhandhavaggapāḷi/Brahmajālasutta/21", "X/Sīlakkhandhavaggaabhinavaṭīkā/Brahmajālasutta/22": "X/Sīlakkhandhavaggapāḷi/Brahmajālasutta/22", "X/Sīlakkhandhavaggaabhinavaṭīkā/Brahmajālasutta/23": "X/Sīlakkhandhavaggapāḷi/Brahmajālasutta/23", "X/Sīlakkhandhavaggaabhinavaṭīkā/Brahmajālasutta/24": "X/Sīlakkhandhavaggapāḷi/Brahmajālasutta/24", "X/Sīlakkhandhavaggaabhinavaṭīkā/Brahmajālasutta/25": "X/Sīlakkhandhavaggapāḷi/Brahmajālasutta/25", "X/Sīlakkhandhavaggaabhinavaṭīkā/Brahmajālasutta/26": "X/Sīlakkhandhavaggapāḷi/Brahmajālasutta/26", "X/Sīlakkhandhavaggaabhinavaṭīkā/Brahmajālasutta/27": "X/Sīlakkhandhavaggapāḷi/Brahmajālasutta/27", "X/Sīlakkhandhavaggaabhinavaṭīkā/Brahmajālasutta/28": "X/Sīlakkhandhavaggapāḷi/Brahmajālasutta/28", "X/Sīlakkhandhavaggaabhinavaṭīkā/Brahmajālasutta/29": "X/Sīlakkhandhavaggapāḷi/Brahmajālasutta/29", "X/Sīlakkhandhavaggaabhinavaṭīkā/Brahmajālasutta/30": "X/Sīlakkhandhavaggapāḷi/Brahmajālasutta/30", "X/Sīlakkhandhavaggaabhinavaṭīkā/Brahmajālasutta/31": "X/Sīlakkhandhavaggapāḷi/Brahmajālasutta/31", "X/Sīlakkhandhavaggaabhinavaṭīkā/Brahmajālasutta/32": "X/Sīlakkhandhavaggapāḷi/Brahmajālasutta/32", "X/Sīlakkhandhavaggaabhinavaṭīkā/Brahmajālasutta/34": "X/Sīlakkhandhavaggapāḷi/Brahmajālasutta/34", "X/Sīlakkhandhavaggaabhinavaṭīkā/Brahmajālasutta/35": "X/Sīlakkhandhavaggapāḷi/Brahmajālasutta/35", "X/Sīlakkhandhavaggaabhinavaṭīkā/Brahmajālasutta/36": "X/Sīlakkhandhavaggapāḷi/Brahmajālasutta/36", "X/Sīlakkhandhavaggaabhinavaṭīkā/Brahmajālasutta/37": "X/Sīlakkhandhavaggapāḷi/Brahmajālasutta/37", "X/Sīlakkhandhavaggaabhinavaṭīkā/Brahmajālasutta/38": "X/Sīlakkhandhavaggapāḷi/Brahmajālasutta/38", "X/Sīlakkhandhavaggaabhinavaṭīkā/Brahmajālasutta/39": "X/Sīlakkhandhavaggapāḷi/Brahmajālasutta/39", "X/Sīlakkhandhavaggaabhinavaṭīkā/Brahmajālasutta/40": "X/Sīlakkhandhavaggapāḷi/Brahmajālasutta/40", "X/Sīlakkhandhavaggaabhinavaṭīkā/Brahmajālasutta/41": "X/Sīlakkhandhavaggapāḷi/Brahmajālasutta/41", "X/Sīlakkhandhavaggaabhinavaṭīkā/Brahmajālasutta/42": "X/Sīlakkhandhavaggapāḷi/Brahmajālasutta/42", "X/Sīlakkhandhavaggaabhinavaṭīkā/Brahmajālasutta/43": "X/Sīlakkhandhavaggapāḷi/Brahmajālasutta/43", "X/Sīlakkhandhavaggaabhinavaṭīkā/Brahmajālasutta/44": "X/Sīlakkhandhavaggapāḷi/Brahmajālasutta/44", "X/Sīlakkhandhavaggaabhinavaṭīkā/Brahmajālasutta/45": "X/Sīlakkhandhavaggapāḷi/Brahmajālasutta/45", "X/Sīlakkhandhavaggaabhinavaṭīkā/Brahmajālasutta/47": "X/Sīlakkhandhavaggapāḷi/Brahmajālasutta/47", "X/Sīlakkhandhavaggaabhinavaṭīkā/Brahmajālasutta/49": "X/Sīlakkhandhavaggapāḷi/Brahmajālasutta/49", "X/Sīlakkhandhavaggaabhinavaṭīkā/Brahmajālasutta/53": "X/Sīlakkhandhavaggapāḷi/Brahmajālasutta/53", "X/Sīlakkhandhavaggaabhinavaṭīkā/Brahmajālasutta/54": "X/Sīlakkhandhavaggapāḷi/Brahmajālasutta/54", "X/Sīlakkhandhavaggaabhinavaṭīkā/Brahmajālasutta/61": "X/Sīlakkhandhavaggapāḷi/Brahmajālasutta/61", "X/Sīlakkhandhavaggaabhinavaṭīkā/Brahmajālasutta/62": "X/Sīlakkhandhavaggapāḷi/Brahmajālasutta/62", "X/Sīlakkhandhavaggaabhinavaṭīkā/Brahmajālasutta/63": "X/Sīlakkhandhavaggapāḷi/Brahmajālasutta/63", "X/Sīlakkhandhavaggaabhinavaṭīkā/Brahmajālasutta/64": "X/Sīlakkhandhavaggapāḷi/Brahmajālasutta/64", "X/Sīlakkhandhavaggaabhinavaṭīkā/Brahmajālasutta/65": "X/Sīlakkhandhavaggapāḷi/Brahmajālasutta/65", "X/Sīlakkhandhavaggaabhinavaṭīkā/Brahmajālasutta/67": "X/Sīlakkhandhavaggapāḷi/Brahmajālasutta/67", "X/Sīlakkhandhavaggaabhinavaṭīkā/Brahmajālasutta/68": "X/Sīlakkhandhavaggapāḷi/Brahmajālasutta/68", "X/Sīlakkhandhavaggaabhinavaṭīkā/Brahmajālasutta/74": "X/Sīlakkhandhavaggapāḷi/Brahmajālasutta/74", "X/Sīlakkhandhavaggaabhinavaṭīkā/Brahmajālasutta/75": "X/Sīlakkhandhavaggapāḷi/Brahmajālasutta/75", "X/Sīlakkhandhavaggaabhinavaṭīkā/Brahmajālasutta/76": "X/Sīlakkhandhavaggapāḷi/Brahmajālasutta/76", "X/Sīlakkhandhavaggaabhinavaṭīkā/Brahmajālasutta/78": "X/Sīlakkhandhavaggapāḷi/Brahmajālasutta/78", "X/Sīlakkhandhavaggaabhinavaṭīkā/Brahmajālasutta/84": "X/Sīlakkhandhavaggapāḷi/Brahmajālasutta/84", "X/Sīlakkhandhavaggaabhinavaṭīkā/Brahmajālasutta/85": "X/Sīlakkhandhavaggapāḷi/Brahmajālasutta/85", "X/Sīlakkhandhavaggaabhinavaṭīkā/Brahmajālasutta/86": "X/Sīlakkhandhavaggapāḷi/Brahmajālasutta/86", "X/Sīlakkhandhavaggaabhinavaṭīkā/Brahmajālasutta/87": "X/Sīlakkhandhavaggapāḷi/Brahmajālasutta/87", "X/Sīlakkhandhavaggaabhinavaṭīkā/Brahmajālasutta/88": "X/Sīlakkhandhavaggapāḷi/Brahmajālasutta/88", "X/Sīlakkhandhavaggaabhinavaṭīkā/Brahmajālasutta/93": "X/Sīlakkhandhavaggapāḷi/Brahmajālasutta/93", "X/Sīlakkhandhavaggaabhinavaṭīkā/Brahmajālasutta/94": "X/Sīlakkhandhavaggapāḷi/Brahmajālasutta/94", "X/Sīlakkhandhavaggaabhinavaṭīkā/Brahmajālasutta/95": "X/Sīlakkhandhavaggapāḷi/Brahmajālasutta/95", "X/Sīlakkhandhavaggaabhinavaṭīkā/Brahmajālasutta/96": "X/Sīlakkhandhavaggapāḷi/Brahmajālasutta/96", "X/Sīlakkhandhavaggaabhinavaṭīkā/Brahmajālasutta/97": "X/Sīlakkhandhavaggapāḷi/Brahmajālasutta/97", "X/Sīlakkhandhavaggaabhinavaṭīkā/Brahmajālasutta/98": "X/Sīlakkhandhavaggapāḷi/Brahmajālasutta/98", "X/Sīlakkhandhavaggaabhinavaṭīkā/Brahmajālasutta/100": "X/Sīlakkhandhavaggapāḷi/Brahmajālasutta/100", "X/Sīlakkhandhavaggaabhinavaṭīkā/Brahmajālasutta/105": "X/Sīlakkhandhavaggapāḷi/Brahmajālasutta/105", "X/Sīlakkhandhavaggaabhinavaṭīkā/Brahmajālasutta/118": "X/Sīlakkhandhavaggapāḷi/Brahmajālasutta/118", "X/Sīlakkhandhavaggaabhinavaṭīkā/Brahmajālasutta/131": "X/Sīlakkhandhavaggapāḷi/Brahmajālasutta/131", "X/Sīlakkhandhavaggaabhinavaṭīkā/Brahmajālasutta/144": "X/Sīlakkhandhavaggapāḷi/Brahmajālasutta/144", "X/Sīlakkhandhavaggaabhinavaṭīkā/Brahmajālasutta/145": "X/Sīlakkhandhavaggapāḷi/Brahmajālasutta/145", "X/Sīlakkhandhavaggaabhinavaṭīkā/Brahmajālasutta/146": "X/Sīlakkhandhavaggapāḷi/Brahmajālasutta/146", "X/Sīlakkhandhavaggaabhinavaṭīkā/Brahmajālasutta/147": "X/Sīlakkhandhavaggapāḷi/Brahmajālasutta/147", "X/Sīlakkhandhavaggaabhinavaṭīkā/Brahmajālasutta/148": "X/Sīlakkhandhavaggapāḷi/Brahmajālasutta/148", "X/Sīlakkhandhavaggaabhinavaṭīkā/Brahmajālasutta/149": "X/Sīlakkhandhavaggapāḷi/Brahmajālasutta/149"}